deepforest/IoU.py
deepforest/__init__.py
deepforest/_version.py
deepforest/augmentations.py
deepforest/callbacks.py
deepforest/download.py
deepforest/evaluate.py
deepforest/main.py
deepforest/model.py
deepforest/predict.py
deepforest/preprocess.py
deepforest/utilities.py
deepforest/visualize.py
deepforest/conf/__init__.py
deepforest/conf/config.yaml
deepforest/conf/schema.py
deepforest/data/2019_YELL_2_528000_4978000_image_crop2.png
deepforest/data/2019_YELL_2_528000_4978000_image_crop2.xml
deepforest/data/2019_YELL_2_541000_4977000_image_crop.png
deepforest/data/2019_YELL_2_541000_4977000_image_crop.xml
deepforest/data/AWPE Pigeon Lake 2020 DJI_0005.JPG
deepforest/data/OSBS_029.csv
deepforest/data/OSBS_029.png
deepforest/data/OSBS_029.tif
deepforest/data/OSBS_029.xml
deepforest/data/SOAP_031.png
deepforest/data/SOAP_061.png
deepforest/data/SOAP_061.xml
deepforest/data/__init__.py
deepforest/data/classes.csv
deepforest/data/example.csv
deepforest/data/testfile_deepforest.csv
deepforest/data/testfile_multi.csv
deepforest/datasets/cropmodel.py
deepforest/datasets/prediction.py
deepforest/datasets/training.py
deepforest/models/DeformableDetr.py
deepforest/models/__init__.py
deepforest/models/retinanet.py
deepforest/scripts/__init__.py
deepforest/scripts/cli.py
deepforest-2.0.0.dist-info/licenses/AUTHORS.md
deepforest-2.0.0.dist-info/licenses/LICENSE
deepforest-2.0.0.dist-info/METADATA
deepforest-2.0.0.dist-info/WHEEL
deepforest-2.0.0.dist-info/entry_points.txt
deepforest-2.0.0.dist-info/top_level.txt
deepforest-2.0.0.dist-info/RECORD
