Metadata-Version: 2.4
Name: deepforest
Version: 2.0.0
Summary: Platform for individual detection from airborne remote sensing including trees, birds, and livestock. Supports multiple detection models, adding models for species classification, and easy fine tuning to particular ecosystems.
Author-email: Ben Weinstein <benweinstein@weecology.org>, Henry Senyondo <henrykironde@gmail.com>, Josh Veitch-Michaelis <j.veitchmichaelis@gmail.com>, Muhammed Magdy <muhammedmagdy1015@gmail.com>, Om Doiphode <omdoiphode161@gmail.com>, Dingyi Fang <imfangdingyi@gmail.com>, Ethan White <ethan@weecology.org>
License: MIT
Project-URL: Documentation, http://deepforest.readthedocs.io/en/latest/
Project-URL: Source, https://github.com/Weecology/DeepForest
Project-URL: Contributors, https://github.com/Weecology/DeepForest/graphs/contributors
Keywords: deep-learning,forest,ecology,computer-vision
Classifier: Development Status :: 6 - Mature
Classifier: License :: OSI Approved :: MIT License
Classifier: Operating System :: MacOS
Classifier: Operating System :: Microsoft :: Windows
Classifier: Operating System :: POSIX
Classifier: Operating System :: Unix
Classifier: Programming Language :: Python :: 3.10
Classifier: Programming Language :: Python :: 3.11
Classifier: Programming Language :: Python :: 3.12
Classifier: Topic :: Scientific/Engineering :: Artificial Intelligence
Classifier: Topic :: Scientific/Engineering :: Image Processing
Classifier: Topic :: Scientific/Engineering :: Image Recognition
Requires-Python: <3.13,>=3.10
License-File: LICENSE
License-File: AUTHORS.md
Requires-Dist: aiohttp
Requires-Dist: aiolimiter
Requires-Dist: albumentations>=2.0.0
Requires-Dist: faster-coco-eval>=1.6.8
Requires-Dist: geopandas
Requires-Dist: h5py
Requires-Dist: huggingface_hub>=0.25.0
Requires-Dist: hydra-core
Requires-Dist: matplotlib
Requires-Dist: numpy<2.0
Requires-Dist: omegaconf
Requires-Dist: opencv-python-headless>=4.5.4
Requires-Dist: pandas
Requires-Dist: pillow>6.2.0
Requires-Dist: psutil
Requires-Dist: pytorch-lightning<3.0.0,>=2.1.0
Requires-Dist: pyyaml>=5.1.0
Requires-Dist: rasterio
Requires-Dist: safetensors<0.6.0
Requires-Dist: setuptools
Requires-Dist: shapely>2.0.0
Requires-Dist: slidingwindow
Requires-Dist: supervision
Requires-Dist: tensorboard
Requires-Dist: timm
Requires-Dist: torch>=2.2.0
Requires-Dist: torchvision>=0.17.0
Requires-Dist: tqdm
Requires-Dist: transformers<4.57.0
Requires-Dist: xmltodict
Provides-Extra: dev
Requires-Dist: build>=1.3.0; extra == "dev"
Requires-Dist: bump-my-version; extra == "dev"
Requires-Dist: comet_ml; extra == "dev"
Requires-Dist: docformatter; extra == "dev"
Requires-Dist: nbqa; extra == "dev"
Requires-Dist: pre-commit; extra == "dev"
Requires-Dist: pytest; extra == "dev"
Requires-Dist: pytest-cov; extra == "dev"
Requires-Dist: pytest-mock; extra == "dev"
Requires-Dist: pytest-profiling; extra == "dev"
Requires-Dist: pytest-xdist; extra == "dev"
Requires-Dist: ruff; extra == "dev"
Requires-Dist: twine; extra == "dev"
Provides-Extra: docs
Requires-Dist: docutils<0.18; extra == "docs"
Requires-Dist: myst-parser; extra == "docs"
Requires-Dist: nbmake; extra == "docs"
Requires-Dist: nbsphinx; extra == "docs"
Requires-Dist: numpydoc; extra == "docs"
Requires-Dist: pydata-sphinx-theme; extra == "docs"
Requires-Dist: recommonmark; extra == "docs"
Requires-Dist: sphinx; extra == "docs"
Requires-Dist: sphinx-design; extra == "docs"
Requires-Dist: sphinx-markdown-tables; extra == "docs"
Requires-Dist: sphinx_rtd_theme; extra == "docs"
Dynamic: license-file
